kitchenai_py/__about__.py
kitchenai_py/__init__.py
kitchenai_py/client.py
kitchenai_py-0.0.2.dist-info/METADATA
kitchenai_py-0.0.2.dist-info/WHEEL
kitchenai_py-0.0.2.dist-info/licenses/LICENSE.txt
kitchenai_py-0.0.2.dist-info/RECORD
